FetchGitHubStats/__init__.py
FetchGitHubStats/dataframe.py
FetchGitHubStats-0.0.3.dist-info/METADATA
FetchGitHubStats-0.0.3.dist-info/WHEEL
FetchGitHubStats-0.0.3.dist-info/top_level.txt
FetchGitHubStats-0.0.3.dist-info/RECORD
